ipie/__init__.py
ipie/_version.py
ipie/config.py
ipie/addons/__init__.py
ipie/addons/free_projection/__init__.py
ipie/addons/free_projection/analysis/__init__.py
ipie/addons/free_projection/analysis/extraction.py
ipie/addons/free_projection/analysis/jackknife.py
ipie/addons/free_projection/analysis/tests/__init__.py
ipie/addons/free_projection/analysis/tests/test_jackknife.py
ipie/addons/free_projection/estimators/__init__.py
ipie/addons/free_projection/estimators/energy.py
ipie/addons/free_projection/estimators/handler.py
ipie/addons/free_projection/estimators/tests/__init__.py
ipie/addons/free_projection/estimators/tests/test_estimators.py
ipie/addons/free_projection/propagation/__init__.py
ipie/addons/free_projection/propagation/free_propagation.py
ipie/addons/free_projection/propagation/tests/__init__.py
ipie/addons/free_projection/propagation/tests/test_generic.py
ipie/addons/free_projection/qmc/__init__.py
ipie/addons/free_projection/qmc/calc.py
ipie/addons/free_projection/qmc/fp_afqmc.py
ipie/addons/free_projection/qmc/options.py
ipie/addons/free_projection/qmc/tests/__init__.py
ipie/addons/free_projection/qmc/tests/test_afqmc_single_det_batch.py
ipie/addons/free_projection/utils/__init__.py
ipie/addons/free_projection/utils/testing.py
ipie/addons/free_projection/walkers/__init__.py
ipie/addons/free_projection/walkers/uhf_walkers.py
ipie/addons/free_projection/walkers/tests/__init__.py
ipie/addons/free_projection/walkers/tests/test_single_det_uhf.py
ipie/addons/thermal/__init__.py
ipie/addons/thermal/analysis/__init__.py
ipie/addons/thermal/analysis/extraction.py
ipie/addons/thermal/analysis/thermal_analysis.py
ipie/addons/thermal/estimators/__init__.py
ipie/addons/thermal/estimators/energy.py
ipie/addons/thermal/estimators/generic.py
ipie/addons/thermal/estimators/greens_function.py
ipie/addons/thermal/estimators/handler.py
ipie/addons/thermal/estimators/local_energy.py
ipie/addons/thermal/estimators/particle_number.py
ipie-0.7.1.dist-info/LICENSE
ipie-0.7.1.dist-info/METADATA
ipie-0.7.1.dist-info/NOTICE
ipie-0.7.1.dist-info/WHEEL
ipie-0.7.1.dist-info/top_level.txt
ipie-0.7.1.dist-info/RECORD
