Metadata-Version: 2.1
Name: ipie
Version: 0.7.1
Summary: Python implementations of Imaginary-time Evolution algorithms
Home-page: http://github.com/linusjoonho/ipie
Author: ipie developers
License: Apache 2.0
Requires-Python: >=3.8.0
License-File: LICENSE
License-File: NOTICE
Requires-Dist: h5py >=3.0.0
Requires-Dist: numpy >=1.20.0
Requires-Dist: scipy >=1.3.0
Requires-Dist: pytest
Requires-Dist: pandas
Requires-Dist: numba
Requires-Dist: plum-dispatch
Provides-Extra: dev
Requires-Dist: black ; extra == 'dev'
Requires-Dist: pytest-xdist ; extra == 'dev'
Requires-Dist: flynt ; extra == 'dev'
Requires-Dist: mpi4py >=3.0.0 ; extra == 'dev'
Provides-Extra: mpi
